fastapi_observable_socket/__init__.py
fastapi_observable_socket/compat.py
fastapi_observable_socket/message.py
fastapi_observable_socket/observable_socket.py
fastapi_observable_socket/response_sender.py
fastapi_observable_socket/route_options.py
fastapi_observable_socket/status.py
fastapi_observable_socket-1.1.1.dist-info/METADATA
fastapi_observable_socket-1.1.1.dist-info/WHEEL
fastapi_observable_socket-1.1.1.dist-info/top_level.txt
fastapi_observable_socket-1.1.1.dist-info/RECORD
