Metadata-Version: 2.4
Name: fastapi-observable-socket
Version: 1.1.1
Summary: A lightweight WebSocket router for FastAPI, fully compatible with the ObservableSocket (JS/TS) client.
Author-email: Alireza Tabatabaeian <contact@fixance.me>
License-Expression: MIT
Project-URL: Homepage, https://github.com/Alireza-Tabatabaeian/fastapi-observable-socket
Project-URL: Documentation, https://github.com/Alireza-Tabatabaeian/fastapi-observable-socket
Project-URL: Repository, https://github.com/Alireza-Tabatabaeian/fastapi-observable-socket
Project-URL: Issues, https://github.com/Alireza-Tabatabaeian/fastapi-observable-socket/issues
Project-URL: Related, https://www.npmjs.com/package/@djanext/observable-socket
Keywords: fastapi,websocket,router,observable,asyncio,realtime,socket,starlette
Classifier: Development Status :: 5 - Production/Stable
Classifier: Framework :: FastAPI
Classifier: Intended Audience :: Developers
Classifier: Operating System :: OS Independent
Classifier: Programming Language :: Python :: 3
Classifier: Programming Language :: Python :: 3.11
Classifier: Programming Language :: Python :: 3.12
Classifier: Programming Language :: Python :: 3.13
Classifier: Topic :: Internet :: WWW/HTTP
Classifier: Topic :: Software Development :: Libraries :: Python Modules
Classifier: Typing :: Typed
Requires-Python: >=3.11
Requires-Dist: fastapi>=0.115
Requires-Dist: pydantic>=2.7
Requires-Dist: starlette>=0.38
